candit/__init__.py
candit/data_loader.py
candit/enjoysport.csv
candit/main.py
candit-5.0.dist-info/METADATA
candit-5.0.dist-info/WHEEL
candit-5.0.dist-info/top_level.txt
candit-5.0.dist-info/RECORD
