Metadata-Version: 2.1
Name: candit
Version: 5.0
Author: Raghul
Author-email: raghulares@gmail.com
Requires-Dist: numpy
Requires-Dist: pandas
